{
  "project_info": {
    "project_number": "390085045430",
    "project_id": "shop-app-7165a",
    "storage_bucket": "shop-app-7165a.appspot.com"
  },
  "client": [
    {
      "client_info": {
        "mobilesdk_app_id": "1:390085045430:android:a606dd246cbaac243c8a17",
        "android_client_info": {
          "package_name": "com.example.shopapp"
        }
      },
      "oauth_client": [
        {
          "client_id": "390085045430-3291n5ipi6t9ahh1n86qn6febhm79s7l.apps.googleusercontent.com",
          "client_type": 1,
          "android_info": {
            "package_name": "com.example.shopapp",
            "certificate_hash": "387e2b369fb2100703b73bc6c41c1a83d468c63e"
          }
        },
        {
          "client_id": "390085045430-fpdl9b3h0toepoduf4fa89rpocegi80d.apps.googleusercontent.com",
          "client_type": 3
        }
      ],
      "api_key": [
        {
          "current_key": "AIzaSyDNo3LbTiDWOFp53DAxqZEiJTLw8njE42g"
        }
      ],
      "services": {
        "appinvite_service": {
          "other_platform_oauth_client": [
            {
              "client_id": "390085045430-fpdl9b3h0toepoduf4fa89rpocegi80d.apps.googleusercontent.com",
              "client_type": 3
            },
            {
              "client_id": "390085045430-3ubqupl95vqbp90h7qatmslou4t5vtn5.apps.googleusercontent.com",
              "client_type": 2,
              "ios_info": {
                "bundle_id": "com.example.shopapp"
              }
            }
          ]
        }
      }
    }
  ],
  "configuration_version": "1"
}